fun_coverage/__init__.py
fun_coverage/fun_coverage.py
fun_coverage-0.2.0.dist-info/LICENSE
fun_coverage-0.2.0.dist-info/WHEEL
fun_coverage-0.2.0.dist-info/entry_points.txt
fun_coverage-0.2.0.dist-info/METADATA
fun_coverage-0.2.0.dist-info/RECORD
