Metadata-Version: 2.1
Name: fun-coverage
Version: 0.2.0
Summary: Report function-level code coverage from the statement-level coverage of coverage.py
Home-page: https://gitlab.com/redballoonsecurity/fun-coverage
License: MIT
Author: Red Balloon Security
Requires-Python: >=3.7,<4.0
Classifier: License :: OSI Approved :: MIT License
Classifier: Operating System :: OS Independent
Classifier: Programming Language :: Python :: 3
Classifier: Programming Language :: Python :: 3.7
Classifier: Programming Language :: Python :: 3.8
Classifier: Programming Language :: Python :: 3.9
Classifier: Programming Language :: Python :: 3.10
Classifier: Programming Language :: Python :: 3.11
Classifier: Programming Language :: Python :: 3
Requires-Dist: coverage (>=6.3.2,<7.0.0)
Requires-Dist: importlib-metadata (>=4.11.4,<5.0.0)
Requires-Dist: termcolor (>=1.1.0,<2.0.0)
Project-URL: Repository, https://gitlab.com/redballoonsecurity/fun-coverage
